jsonc/__init__.py
jsoncparser-1.1.0.dist-info/LICENSE
jsoncparser-1.1.0.dist-info/METADATA
jsoncparser-1.1.0.dist-info/WHEEL
jsoncparser-1.1.0.dist-info/top_level.txt
jsoncparser-1.1.0.dist-info/RECORD
