Metadata-Version: 2.1
Name: jsoncparser
Version: 1.1.0
Summary: A Python package to enable reading/writing of json files with comments
Home-page: https://github.com/jfcarter2358/jsonc
Author: John Carter
Author-email: jfcarter2358@gmail.com
License: MIT
Platform: UNKNOWN
Requires-Python: >=3.7
License-File: LICENSE
